pydacharts/__init__.py
pydacharts/chart_utils.py
pydacharts/chartjs_types.py
pydacharts/charts.py
pydacharts/color.py
pydacharts/elements.py
pydacharts/models.py
pydacharts/py.typed
pydacharts/plugins/__init__.py
pydacharts/plugins/datalabels.py
pydacharts/plugins/doughnutlabel.py
pydacharts/plugins/sankey.py
pydacharts-0.2.0.dist-info/METADATA
pydacharts-0.2.0.dist-info/WHEEL
pydacharts-0.2.0.dist-info/RECORD
