Metadata-Version: 2.3
Name: pydacharts
Version: 0.2.0
Summary: ChartJS Python integration
Author-email: Josh Brooks <josh@catalpa.io>, Roberto Maurizzi <roberto@catalpa.io>
Classifier: Development Status :: 4 - Beta
Classifier: Intended Audience :: Developers
Classifier: License :: OSI Approved :: MIT License
Classifier: Programming Language :: Python :: 3
Classifier: Programming Language :: Python :: 3.11
Classifier: Topic :: Software Development :: Build Tools
Requires-Python: >=3.11
Requires-Dist: pydantic
Provides-Extra: serve
Requires-Dist: fastapi[standard]>=0.115.0; extra == 'serve'
Requires-Dist: jinja2>=3.1.4; extra == 'serve'
